com/__init__.py
com/cleverworld/__init__.py
com/cleverworld/spring/Terminator.py
com/cleverworld/spring/__init__.py
com/cleverworld/spring/terminator/BusinessConnector.py
com/cleverworld/spring/terminator/CommandExecutor.py
com/cleverworld/spring/terminator/Terminator.py
com/cleverworld/spring/terminator/Utils.py
com/cleverworld/spring/terminator/__init__.py
com/cleverworld/spring/terminator/conf/__init__.py
com/cleverworld/spring/terminator/conf/app.yaml
ProxyTerminator-1.4.dist-info/METADATA
ProxyTerminator-1.4.dist-info/WHEEL
ProxyTerminator-1.4.dist-info/entry_points.txt
ProxyTerminator-1.4.dist-info/top_level.txt
ProxyTerminator-1.4.dist-info/RECORD
