Metadata-Version: 2.1
Name: ProxyTerminator
Version: 1.4
Summary: network Terminator terminal
Home-page: https://github.com/davify/Terminator.git
Author: SpringVi
Author-email: springvi@qq.com
License: GPLv3
Keywords: Terminator,terminal,network,intranet
Platform: 3.7
Classifier: Development Status :: 6 - Mature
Classifier: Topic :: Utilities
Classifier: Programming Language :: Python :: 3
Classifier: Programming Language :: Python :: 3.5
Classifier: Programming Language :: Python :: 3.5
Classifier: Programming Language :: Python :: 3.6
Classifier: Programming Language :: Python :: 3.7
Classifier: Topic :: Utilities
Classifier: Topic :: Internet :: Proxy Servers
Classifier: Programming Language :: Python :: Implementation :: CPython
Classifier: License :: OSI Approved :: GNU General Public License (GPL)
Requires-Dist: PyYAML (>=3.13)
